{
  "name" : "Set 3",
  "data" : [
    {"startTime": "01:51", "endTime": "02:07", "duration": "16m", "type": "light sleep"},
    {"startTime": "02:07", "endTime": "02:13", "duration": "6m", "type": "awake"},
    {"startTime": "02:13", "endTime": "02:30", "duration": "17m", "type": "light sleep"},
    {"startTime": "02:30", "endTime": "03:04", "duration": "34m", "type": "deep sleep"},
    {"startTime": "03:04", "endTime": "03:09", "duration":                "5m", "type": "REM sleep"},
    {"startTime": "03:09", "endTime": "03:11", "duration": "2m", "type": "awake"},
    {"startTime": "03:11", "endTime": "03:12", "duration": "1m", "type": "light sleep"},
    {"startTime": "03:12", "endTime": "03:13", "duration": "1m", "type": "awake"},
    {"startTime": "03:13", "endTime": "03:16", "duration": "3m", "type": "light sleep"},
    {"startTime": "03:16", "endTime": "03:17", "duration": "1m", "type": "awake"},
    {"startTime": "03:17", "endTime": "03:32", "duration": "15m", "type": "light sleep"},
    {"startTime": "03:32", "endTime": "03:43", "duration": "11m", "type": "deep sleep"},
    {"startTime": "03:43", "endTime": "03:47", "duration": "4m", "type": "light sleep"},
    {"startTime": "03:47", "endTime": "03:55", "duration": "8m", "type": "deep sleep"},
    {"startTime": "03:55", "endTime": "03:59", "duration": "4m", "type": "awake"},
    {"startTime": "03:59", "endTime": "04:10", "duration": "11m", "type": "light sleep"},
    {"startTime": "04:10", "endTime": "04:19", "duration": "9m", "type": "REM sleep"},
    {"startTime": "04:19", "endTime": "04:20", "duration": "1m", "type": "awake"},
    {"startTime": "04:20", "endTime": "04:25", "duration": "5m", "type": "REM sleep"},
    {"startTime": "04:25", "endTime": "04:26", "duration": "1m", "type": "awake"},
    {"startTime": "04:26", "endTime": "04:34", "duration": "8m", "type": "REM sleep"},
    {"startTime": "04:34", "endTime": "04:36", "duration": "2m", "type": "light sleep"},
    {"startTime": "04:36", "endTime": "04:38", "duration": "2m", "type": "REM sleep"},
    {"startTime": "04:38", "endTime": "04:40", "duration": "2m", "type": "awake"},
    {"startTime": "04:40", "endTime": "04:47", "duration": "7m", "type": "light sleep"},
    {"startTime": "04:47", "endTime": "04:48", "duration": "1m", "type": "awake"},
    {"startTime": "04:48", "endTime": "05:03", "duration": "15m", "type": "light sleep"},
    {"startTime": "05:03", "endTime": "05:28", "duration": "25m", "type": "deep sleep"},
    {"startTime": "05:28", "endTime": "05:29", "duration": "1m", "type": "awake"},
    {"startTime": "05:29", "endTime": "05:32", "duration": "3m", "type": "light sleep"},
    {"startTime": "05:32", "endTime": "05:33", "duration": "1m", "type": "awake"},
    {"startTime": "05:33", "endTime": "05:38", "duration": "5m", "type": "light sleep"},
    {"startTime": "05:38", "endTime": "05:39", "duration": "1m", "type": "REM sleep"},
    {"startTime": "05:39", "endTime": "05:40", "duration": "1m", "type": "awake"},
    {"startTime": "05:40", "endTime": "05:43", "duration": "3m", "type": "light sleep"},
    {"startTime": "05:43", "endTime": "05:44", "duration": "1m", "type": "REM sleep"},
    {"startTime": "05:44", "endTime": "05:45", "duration": "1m", "type": "awake"},
    {"startTime": "05:45", "endTime": "05:46", "duration": "1m", "type": "light sleep"},
    {"startTime": "05:46", "endTime": "05:52", "duration": "6m", "type": "awake"},
    {"startTime": "05:52", "endTime": "05:55", "duration": "3m", "type": "light sleep"},
    {"startTime": "05:55", "endTime": "05:57", "duration": "2m", "type": "awake"},
    {"startTime": "05:57", "endTime": "06:05", "duration": "8m", "type": "light sleep"},
    {"startTime": "06:05", "endTime": "06:06", "duration": "1m", "type": "REM sleep"},
    {"startTime": "06:06", "endTime": "06:07", "duration": "1m", "type": "awake"},
    {"startTime": "06:07", "endTime": "06:09", "duration": "2m", "type": "light sleep"},
    {"startTime": "06:09", "endTime": "06:10", "duration": "1m", "type": "awake"},
    {"startTime": "06:10", "endTime": "06:13", "duration": "3m", "type": "light sleep"},
    {"startTime": "06:13", "endTime": "06:18", "duration": "5m", "type": "awake"},
    {"startTime": "06:18", "endTime": "06:20", "duration": "2m", "type": "light sleep"},
    {"startTime": "06:20", "endTime": "06:21", "duration": "1m", "type": "REM sleep"},
    {"startTime": "06:21", "endTime": "06:22", "duration": "1m", "type": "awake"},
    {"startTime": "06:22", "endTime": "06:26", "duration": "4m", "type": "REM sleep"},
    {"startTime": "06:26", "endTime": "06:27", "duration": "1m", "type": "awake"},
    {"startTime": "06:27", "endTime": "06:28", "duration": "1m", "type": "light sleep"},
    {"startTime": "06:28", "endTime": "06:29", "duration": "1m", "type": "REM sleep"},
    {"startTime": "06:29", "endTime": "06:30", "duration": "1m", "type": "awake"},
    {"startTime": "06:30", "endTime": "06:39", "duration": "9m", "type": "light sleep"},
    {"startTime": "06:39", "endTime": "06:40", "duration": "1m", "type": "REM sleep"},
    {"startTime": "06:40", "endTime": "06:41", "duration": "1m", "type": "light sleep"},
    {"startTime": "06:41", "endTime": "06:46", "duration": "5m", "type": "awake"},
    {"startTime": "06:46", "endTime": "06:49", "duration": "3m", "type": "light sleep"},
    {"startTime": "06:49", "endTime": "06:50", "duration": "1m", "type": "awake"},
    {"startTime": "06:50", "endTime": "07:09", "duration": "19m", "type": "light sleep"},
    {"startTime": "07:09", "endTime": "07:10", "duration": "1m", "type": "awake"},
    {"startTime": "07:10", "endTime": "07:13", "duration": "3m", "type": "light sleep"},
    {"startTime": "07:13", "endTime": "07:15", "duration": "2m", "type": "awake"},
    {"startTime": "07:15", "endTime": "07:27", "duration": "12m", "type": "light sleep"},
    {"startTime": "07:27", "endTime": "07:29", "duration": "2m", "type": "awake"},
    {"startTime": "07:29", "endTime": "07:36", "duration": "7m", "type": "light sleep"},
    {"startTime": "07:36", "endTime": "07:37", "duration": "1m", "type": "REM sleep"},
    {"startTime": "07:37", "endTime": "07:38", "duration": "1m", "type": "awake"},
    {"startTime": "07:38", "endTime": "07:43", "duration": "5m", "type": "light sleep"},
    {"startTime": "07:43", "endTime": "07:45", "duration": "2m", "type": "awake"}
  ],
  "targets": {
    "PR": 86,
    "RST": 85,
    "MR": 56,
    "SC": 76,
    "CYL": 5,
    "DSCYL": 34
  }
}